ugrid_checks/__init__.py
ugrid_checks/__main__.py
ugrid_checks/_var_data.py
ugrid_checks/check.py
ugrid_checks/cli.py
ugrid_checks/nc_dataset_scan.py
ugrid_checks/scan_utils.py
ugrid_checks/ugrid_logger.py
ugrid_checks-0.2.0.dist-info/LICENSE
ugrid_checks-0.2.0.dist-info/METADATA
ugrid_checks-0.2.0.dist-info/WHEEL
ugrid_checks-0.2.0.dist-info/entry_points.txt
ugrid_checks-0.2.0.dist-info/top_level.txt
ugrid_checks-0.2.0.dist-info/RECORD
