Metadata-Version: 2.1
Name: ugrid-checks
Version: 0.2.0
Summary: Check netcdf files for conformance with UGRID specifications
Home-page: https://github.com/pp-mo/ugrid-checks
Author: pp-mo
Author-email: patrick.peglar@metoffice.gov.uk
License: BSD 3-Clause License
Project-URL: Code, https://github.com/pp-mo/ugrid-checks
Project-URL: Discussions, https://github.com/pp-mo/ugrid-checks/discussions
Project-URL: Documentation, https://github.com/pp-mo/ugrid-checks
Project-URL: Issues, https://github.com/pp-mo/ugrid-checks/issues
Keywords: mesh,ugrid
Classifier: Development Status :: 3 - Alpha
Classifier: Intended Audience :: Science/Research
Classifier: License :: OSI Approved :: BSD License
Classifier: Natural Language :: English
Classifier: Operating System :: OS Independent
Classifier: Programming Language :: Python :: 3 :: Only
Classifier: Programming Language :: Python :: 3.7
Classifier: Programming Language :: Python :: 3.8
Classifier: Programming Language :: Python :: 3.9
Classifier: Programming Language :: Python :: 3.10
Classifier: Topic :: Scientific/Engineering
Requires-Python: >=3.7
License-File: LICENSE
Requires-Dist: netCDF4
Provides-Extra: dev
Requires-Dist: pre-commit ; extra == 'dev'
Provides-Extra: test
Requires-Dist: pytest (>=6.0) ; extra == 'test'
